juanpy/__init__.py
juanpy/max_min.py
juanpy-1.0.0.dist-info/LICENSE.txt
juanpy-1.0.0.dist-info/METADATA
juanpy-1.0.0.dist-info/WHEEL
juanpy-1.0.0.dist-info/top_level.txt
juanpy-1.0.0.dist-info/RECORD
