Metadata-Version: 2.1
Name: juanpy
Version: 1.0.0
Summary: UNKNOWN
Home-page: https://github.com/gauss314/juanpy
Author: Juan Pablo Pisano
Author-email: jpp.programacion@gmail.com
License: UNKNOWN
Keywords: Ullua,El taco no,manteca
Platform: UNKNOWN
Classifier: Programming Language :: Python :: 3
Classifier: License :: OSI Approved :: MIT License
Classifier: Operating System :: OS Independent
Requires-Python: >=3.6
Requires-Dist: pandas
Requires-Dist: matplotlib
Requires-Dist: yfinance
Requires-Dist: datetime
